Bin2Dec/Bin2Dec.py
Bin2Dec/__init__.py
Bin2Dec12/Bin2Dec12.py
Bin2Dec12/__init__.py
bin2dec12-0.0.5.dist-info/METADATA
bin2dec12-0.0.5.dist-info/WHEEL
bin2dec12-0.0.5.dist-info/top_level.txt
bin2dec12-0.0.5.dist-info/RECORD
